RG/DTW.py
RG/DTW_batch.py
RG/EMSC.py
RG/ICA.py
RG/LDA.py
RG/MCR.py
RG/MSC.py
RG/NPLS_cal.py
RG/NPLS_val.py
RG/PCA.py
RG/PCA_ellipse.py
RG/PLS.py
RG/R2.py
RG/SAM.py
RG/SNV.py
RG/VIF.py
RG/VIP.py
RG/__init__.py
RG/autoscale.py
RG/axaline.py
RG/baseline.py
RG/cPCA.py
RG/center.py
RG/colorspectra.py
RG/corr_reorder.py
RG/correlated_matrix.py
RG/detrend.py
RG/email.py
RG/interactions.py
RG/lags.py
RG/loadmat.py
RG/mbPLS.py
RG/normplot.py
RG/pcorrcoef.py
RG/regress.py
RG/reset.py
RG/savitzky_golay.py
RG/xlsread.py
RG-0.0.75.dist-info/METADATA
RG-0.0.75.dist-info/WHEEL
RG-0.0.75.dist-info/top_level.txt
RG-0.0.75.dist-info/RECORD
