Metadata-Version: 2.1
Name: RG
Version: 0.0.75
Summary: Ryan's go-to Python functions
Home-page: https://www.usherbrooke.ca/gchimiquebiotech/departement/professeurs/ryan-gosselin/
Author: Ryan Gosselin
Author-email: ryan.gosselin@usherbrooke.ca
License: UNKNOWN
Platform: UNKNOWN
Classifier: Programming Language :: Python :: 3
Classifier: License :: OSI Approved :: MIT License
Classifier: Operating System :: OS Independent
